file_encryptor_atharva_project_14/__init__.py
file_encryptor_atharva_project_14/encryptor.py
file_encryptor_atharva_project_14-0.1.dist-info/METADATA
file_encryptor_atharva_project_14-0.1.dist-info/WHEEL
file_encryptor_atharva_project_14-0.1.dist-info/top_level.txt
file_encryptor_atharva_project_14-0.1.dist-info/RECORD
