Metadata-Version: 2.1
Name: file_encryptor_atharva_project_14
Version: 0.1
Summary: A file encryption package
Home-page: https://github.com/Zaid-S-Pathan/file_encryptor
Author: Zaid Pathan
Author-email: zaidspathan@gmail.com
Classifier: Programming Language :: Python :: 3
Classifier: Operating System :: OS Independent
Requires-Dist: cryptography
